[
  {
    "ruleid": "e67bb24c-b5e5-453f-9daf-931382c8457f",
    "homeid": 50715,
    "active_from": "10:00:00",
    "active_to": "22:00:00",
    "conditions": [
      {
        "room_name": "living",
        "temperature_higher": 25,
        "vacant": false
      }
    ],
    "action": "turn_on(AC_living)"
  },
  {
    "ruleid": "db97e076-75a2-4f6b-a2fc-19b72773f56f",
    "homeid": 50715,
    "active_from": "19:00:00",
    "conditions": [
      {
        "room_name": "bedroom",
        "pm25_higher": 50
      }
    ],
    "action": "turn_on(airfilter_bedroom)"
  },
  {
    "ruleid": "6e2a775b-e09f-4448-8364-4da983c87a32",
    "homeid": 50715,
    "active_from": "20:00:00",
    "conditions": [
      {
        "room_name": "living",
        "vacant": true
      },
      {
        "room": "bedroom",
        "vacant": true
      }
    ],
    "action": "turn_off(heating)"
  }
]
