{
  "type": "source",
  "canonicalizer": "system",
  "format": {
    "name": "csv",
    "charset": "UTF-8",
    "delimiter": ";",
    "header": [
      "id",
      "name",
      "sizing",
      "weight_in_gram",
      "type",
      "category",
      "usda_id",
      "updated"
    ]
  },
  "identifier": "products",
  "schema": "flexible",
  "connector": {
    "directoryURI": "/Users/henneberger/sqrl/sqrl-integration-tests/../sqrl-examples/udf/data/",
    "fileURIs": [],
    "filenamePattern": "^([^\\.]+?)(?:_part.*)?$",
    "name": "file"
  }
}